{"get": "fixtures/statistics", "parameters": {"fixture": "1213401"}, "errors": [], "results": 2, "paging": {"current": 1, "total": 1}, "response": [{"team": {"id": 1393, "name": "Union St. Gilloise", "logo": "https://media.api-sports.io/football/teams/1393.png"}, "statistics": [{"type": "Shots on Goal", "value": 9}, {"type": "Shots off Goal", "value": 10}, {"type": "Total Shots", "value": 19}, {"type": "Blocked Shots", "value": 0}, {"type": "Shots insidebox", "value": 13}, {"type": "Shots outsidebox", "value": 6}, {"type": "Fouls", "value": 13}, {"type": "Corner Kicks", "value": 9}, {"type": "Offsides", "value": 0}, {"type": "Ball Possession", "value": "54%"}, {"type": "Yellow Cards", "value": 4}, {"type": "Red Cards", "value": null}, {"type": "Goalkeeper Saves", "value": 3}, {"type": "Total passes", "value": 465}, {"type": "Passes accurate", "value": 366}, {"type": "Passes %", "value": "79%"}, {"type": "expected_goals", "value": "2.01"}, {"type": "goals_prevented", "value": 1}]}, {"team": {"id": 266, "name": "KV Mechelen", "logo": "https://media.api-sports.io/football/teams/266.png"}, "statistics": [{"type": "Shots on Goal", "value": 4}, {"type": "Shots off Goal", "value": 5}, {"type": "Total Shots", "value": 11}, {"type": "Blocked Shots", "value": 2}, {"type": "Shots insidebox", "value": 8}, {"type": "Shots outsidebox", "value": 3}, {"type": "Fouls", "value": 9}, {"type": "Corner Kicks", "value": 5}, {"type": "Offsides", "value": 4}, {"type": "Ball Possession", "value": "46%"}, {"type": "Yellow Cards", "value": 1}, {"type": "Red Cards", "value": null}, {"type": "Goalkeeper Saves", "value": 9}, {"type": "Total passes", "value": 397}, {"type": "Passes accurate", "value": 299}, {"type": "Passes %", "value": "75%"}, {"type": "expected_goals", "value": "1.14"}, {"type": "goals_prevented", "value": 1}]}]}