{"get": "fixtures/statistics", "parameters": {"fixture": "76533"}, "errors": [], "results": 2, "paging": {"current": 1, "total": 1}, "response": [{"team": {"id": 366, "name": "IFK Goteborg", "logo": "https://media.api-sports.io/football/teams/366.png"}, "statistics": [{"type": "Shots on Goal", "value": 4}, {"type": "Shots off Goal", "value": 7}, {"type": "Total Shots", "value": 15}, {"type": "Blocked Shots", "value": 4}, {"type": "Shots insidebox", "value": 7}, {"type": "Shots outsidebox", "value": 8}, {"type": "Fouls", "value": 10}, {"type": "Corner Kicks", "value": 2}, {"type": "Offsides", "value": 1}, {"type": "Ball Possession", "value": "45%"}, {"type": "Yellow Cards", "value": 3}, {"type": "Red Cards", "value": null}, {"type": "Goalkeeper Saves", "value": 2}, {"type": "Total passes", "value": 514}, {"type": "Passes accurate", "value": 420}, {"type": "Passes %", "value": "82%"}]}, {"team": {"id": 378, "name": "IFK Norrkoping", "logo": "https://media.api-sports.io/football/teams/378.png"}, "statistics": [{"type": "Shots on Goal", "value": 2}, {"type": "Shots off Goal", "value": 4}, {"type": "Total Shots", "value": 8}, {"type": "Blocked Shots", "value": 2}, {"type": "Shots insidebox", "value": 4}, {"type": "Shots outsidebox", "value": 4}, {"type": "Fouls", "value": 11}, {"type": "Corner Kicks", "value": 5}, {"type": "Offsides", "value": 2}, {"type": "Ball Possession", "value": "55%"}, {"type": "Yellow Cards", "value": 0}, {"type": "Red Cards", "value": null}, {"type": "Goalkeeper Saves", "value": 4}, {"type": "Total passes", "value": 604}, {"type": "Passes accurate", "value": 497}, {"type": "Passes %", "value": "82%"}]}]}