{"get": "fixtures/statistics", "parameters": {"fixture": "719521"}, "errors": [], "results": 2, "paging": {"current": 1, "total": 1}, "response": [{"team": {"id": 169, "name": "Eintracht Frankfurt", "logo": "https://media.api-sports.io/football/teams/169.png"}, "statistics": [{"type": "Shots on Goal", "value": 7}, {"type": "Shots off Goal", "value": 7}, {"type": "Total Shots", "value": 18}, {"type": "Blocked Shots", "value": 4}, {"type": "Shots insidebox", "value": 16}, {"type": "Shots outsidebox", "value": 2}, {"type": "Fouls", "value": 7}, {"type": "Corner Kicks", "value": 10}, {"type": "Offsides", "value": 1}, {"type": "Ball Possession", "value": "68%"}, {"type": "Yellow Cards", "value": 4}, {"type": "Red Cards", "value": null}, {"type": "Goalkeeper Saves", "value": 3}, {"type": "Total passes", "value": 659}, {"type": "Passes accurate", "value": 531}, {"type": "Passes %", "value": "81%"}]}, {"team": {"id": 188, "name": "Arminia Bielefeld", "logo": "https://media.api-sports.io/football/teams/188.png"}, "statistics": [{"type": "Shots on Goal", "value": 5}, {"type": "Shots off Goal", "value": 3}, {"type": "Total Shots", "value": 8}, {"type": "Blocked Shots", "value": 0}, {"type": "Shots insidebox", "value": 7}, {"type": "Shots outsidebox", "value": 1}, {"type": "Fouls", "value": 10}, {"type": "Corner Kicks", "value": 1}, {"type": "Offsides", "value": 3}, {"type": "Ball Possession", "value": "32%"}, {"type": "Yellow Cards", "value": 2}, {"type": "Red Cards", "value": null}, {"type": "Goalkeeper Saves", "value": 7}, {"type": "Total passes", "value": 319}, {"type": "Passes accurate", "value": 190}, {"type": "Passes %", "value": "60%"}]}]}