{"get": "fixtures/statistics", "parameters": {"fixture": "1203069"}, "errors": [], "results": 2, "paging": {"current": 1, "total": 1}, "response": [{"team": {"id": 345, "name": "Zaglebie Lubin", "logo": "https://media.api-sports.io/football/teams/345.png"}, "statistics": [{"type": "Shots on Goal", "value": 7}, {"type": "Shots off Goal", "value": 5}, {"type": "Total Shots", "value": 17}, {"type": "Blocked Shots", "value": 5}, {"type": "Shots insidebox", "value": 6}, {"type": "Shots outsidebox", "value": 11}, {"type": "Fouls", "value": 11}, {"type": "Corner Kicks", "value": 6}, {"type": "Offsides", "value": 1}, {"type": "Ball Possession", "value": "44%"}, {"type": "Yellow Cards", "value": 3}, {"type": "Red Cards", "value": null}, {"type": "Goalkeeper Saves", "value": 1}, {"type": "Total passes", "value": 282}, {"type": "Passes accurate", "value": 186}, {"type": "Passes %", "value": "66%"}, {"type": "expected_goals", "value": "1.17"}, {"type": "goals_prevented", "value": null}]}, {"team": {"id": 337, "name": "Slask Wroclaw", "logo": "https://media.api-sports.io/football/teams/337.png"}, "statistics": [{"type": "Shots on Goal", "value": 1}, {"type": "Shots off Goal", "value": 5}, {"type": "Total Shots", "value": 10}, {"type": "Blocked Shots", "value": 4}, {"type": "Shots insidebox", "value": 6}, {"type": "Shots outsidebox", "value": 4}, {"type": "Fouls", "value": 16}, {"type": "Corner Kicks", "value": 6}, {"type": "Offsides", "value": 0}, {"type": "Ball Possession", "value": "56%"}, {"type": "Yellow Cards", "value": 4}, {"type": "Red Cards", "value": null}, {"type": "Goalkeeper Saves", "value": 4}, {"type": "Total passes", "value": 357}, {"type": "Passes accurate", "value": 268}, {"type": "Passes %", "value": "75%"}, {"type": "expected_goals", "value": "0.24"}, {"type": "goals_prevented", "value": null}]}]}