{"get": "fixtures/statistics", "parameters": {"fixture": "663567"}, "errors": [], "results": 2, "paging": {"current": 1, "total": 1}, "response": [{"team": {"id": 366, "name": "IFK Goteborg", "logo": "https://media.api-sports.io/football/teams/366.png"}, "statistics": [{"type": "Shots on Goal", "value": 3}, {"type": "Shots off Goal", "value": 4}, {"type": "Total Shots", "value": 10}, {"type": "Blocked Shots", "value": 3}, {"type": "Shots insidebox", "value": 6}, {"type": "Shots outsidebox", "value": 4}, {"type": "Fouls", "value": 14}, {"type": "Corner Kicks", "value": 6}, {"type": "Offsides", "value": 3}, {"type": "Ball Possession", "value": "62%"}, {"type": "Yellow Cards", "value": 2}, {"type": "Red Cards", "value": null}, {"type": "Goalkeeper Saves", "value": 0}, {"type": "Total passes", "value": 566}, {"type": "Passes accurate", "value": 449}, {"type": "Passes %", "value": "79%"}]}, {"team": {"id": 2171, "name": "Varbergs BoIS FC", "logo": "https://media.api-sports.io/football/teams/2171.png"}, "statistics": [{"type": "Shots on Goal", "value": 2}, {"type": "Shots off Goal", "value": 1}, {"type": "Total Shots", "value": 5}, {"type": "Blocked Shots", "value": 2}, {"type": "Shots insidebox", "value": 4}, {"type": "Shots outsidebox", "value": 1}, {"type": "Fouls", "value": 19}, {"type": "Corner Kicks", "value": 0}, {"type": "Offsides", "value": 2}, {"type": "Ball Possession", "value": "38%"}, {"type": "Yellow Cards", "value": 1}, {"type": "Red Cards", "value": null}, {"type": "Goalkeeper Saves", "value": 2}, {"type": "Total passes", "value": 355}, {"type": "Passes accurate", "value": 241}, {"type": "Passes %", "value": "68%"}]}]}