{"get": "fixtures/statistics", "parameters": {"fixture": "1238061"}, "errors": [], "results": 2, "paging": {"current": 1, "total": 1}, "response": [{"team": {"id": 3563, "name": "Adana Demirspor", "logo": "https://media.api-sports.io/football/teams/3563.png"}, "statistics": [{"type": "Shots on Goal", "value": 3}, {"type": "Shots off Goal", "value": 1}, {"type": "Total Shots", "value": 5}, {"type": "Blocked Shots", "value": 1}, {"type": "Shots insidebox", "value": 3}, {"type": "Shots outsidebox", "value": 2}, {"type": "Fouls", "value": 19}, {"type": "Corner Kicks", "value": 0}, {"type": "Offsides", "value": 3}, {"type": "Ball Possession", "value": "39%"}, {"type": "Yellow Cards", "value": 4}, {"type": "Red Cards", "value": null}, {"type": "Goalkeeper Saves", "value": 5}, {"type": "Total passes", "value": 285}, {"type": "Passes accurate", "value": 196}, {"type": "Passes %", "value": "69%"}, {"type": "expected_goals", "value": "1.32"}, {"type": "goals_prevented", "value": 0}]}, {"team": {"id": 1005, "name": "Antalyaspor", "logo": "https://media.api-sports.io/football/teams/1005.png"}, "statistics": [{"type": "Shots on Goal", "value": 8}, {"type": "Shots off Goal", "value": 4}, {"type": "Total Shots", "value": 17}, {"type": "Blocked Shots", "value": 5}, {"type": "Shots insidebox", "value": 15}, {"type": "Shots outsidebox", "value": 2}, {"type": "Fouls", "value": 12}, {"type": "Corner Kicks", "value": 9}, {"type": "Offsides", "value": 7}, {"type": "Ball Possession", "value": "61%"}, {"type": "Yellow Cards", "value": 6}, {"type": "Red Cards", "value": null}, {"type": "Goalkeeper Saves", "value": 2}, {"type": "Total passes", "value": 426}, {"type": "Passes accurate", "value": 330}, {"type": "Passes %", "value": "77%"}, {"type": "expected_goals", "value": "3.05"}, {"type": "goals_prevented", "value": 0}]}]}