{"get": "fixtures/statistics", "parameters": {"fixture": "569484"}, "errors": [], "results": 2, "paging": {"current": 1, "total": 1}, "response": [{"team": {"id": 252, "name": "Aberdeen", "logo": "https://media.api-sports.io/football/teams/252.png"}, "statistics": [{"type": "Shots on Goal", "value": 5}, {"type": "Shots off Goal", "value": 1}, {"type": "Total Shots", "value": 7}, {"type": "Blocked Shots", "value": 1}, {"type": "Shots insidebox", "value": 6}, {"type": "Shots outsidebox", "value": 1}, {"type": "Fouls", "value": 11}, {"type": "Corner Kicks", "value": 1}, {"type": "Offsides", "value": 1}, {"type": "Ball Possession", "value": "44%"}, {"type": "Yellow Cards", "value": 0}, {"type": "Red Cards", "value": null}, {"type": "Goalkeeper Saves", "value": 1}, {"type": "Total passes", "value": 350}, {"type": "Passes accurate", "value": 237}, {"type": "Passes %", "value": "68%"}]}, {"team": {"id": 255, "name": "Livingston", "logo": "https://media.api-sports.io/football/teams/255.png"}, "statistics": [{"type": "Shots on Goal", "value": 2}, {"type": "Shots off Goal", "value": 2}, {"type": "Total Shots", "value": 10}, {"type": "Blocked Shots", "value": 6}, {"type": "Shots insidebox", "value": 8}, {"type": "Shots outsidebox", "value": 2}, {"type": "Fouls", "value": 16}, {"type": "Corner Kicks", "value": 3}, {"type": "Offsides", "value": 0}, {"type": "Ball Possession", "value": "56%"}, {"type": "Yellow Cards", "value": 2}, {"type": "Red Cards", "value": null}, {"type": "Goalkeeper Saves", "value": 3}, {"type": "Total passes", "value": 446}, {"type": "Passes accurate", "value": 322}, {"type": "Passes %", "value": "72%"}]}]}