{"get": "fixtures/statistics", "parameters": {"fixture": "1211454"}, "errors": [], "results": 2, "paging": {"current": 1, "total": 1}, "response": [{"team": {"id": 5111, "name": "Kecskem\u00e9ti TE", "logo": "https://media.api-sports.io/football/teams/5111.png"}, "statistics": [{"type": "Shots on Goal", "value": 3}, {"type": "Shots off Goal", "value": 1}, {"type": "Total Shots", "value": 5}, {"type": "Blocked Shots", "value": 1}, {"type": "Shots insidebox", "value": 4}, {"type": "Shots outsidebox", "value": 1}, {"type": "Fouls", "value": 16}, {"type": "Corner Kicks", "value": 1}, {"type": "Offsides", "value": 0}, {"type": "Ball Possession", "value": "43%"}, {"type": "Yellow Cards", "value": 2}, {"type": "Red Cards", "value": 1}, {"type": "Goalkeeper Saves", "value": 1}, {"type": "Total passes", "value": 406}, {"type": "Passes accurate", "value": 327}, {"type": "Passes %", "value": "81%"}, {"type": "expected_goals", "value": null}, {"type": "goals_prevented", "value": null}]}, {"team": {"id": 610, "name": "Feh\u00e9rv\u00e1r FC", "logo": "https://media.api-sports.io/football/teams/610.png"}, "statistics": [{"type": "Shots on Goal", "value": 3}, {"type": "Shots off Goal", "value": 6}, {"type": "Total Shots", "value": 12}, {"type": "Blocked Shots", "value": 3}, {"type": "Shots insidebox", "value": 8}, {"type": "Shots outsidebox", "value": 4}, {"type": "Fouls", "value": 6}, {"type": "Corner Kicks", "value": 0}, {"type": "Offsides", "value": 3}, {"type": "Ball Possession", "value": "57%"}, {"type": "Yellow Cards", "value": 4}, {"type": "Red Cards", "value": 1}, {"type": "Goalkeeper Saves", "value": 1}, {"type": "Total passes", "value": 551}, {"type": "Passes accurate", "value": 471}, {"type": "Passes %", "value": "85%"}, {"type": "expected_goals", "value": null}, {"type": "goals_prevented", "value": null}]}]}