{"get": "fixtures/statistics", "parameters": {"fixture": "872505"}, "errors": [], "results": 2, "paging": {"current": 1, "total": 1}, "response": [{"team": {"id": 415, "name": "Twente", "logo": "https://media.api-sports.io/football/teams/415.png"}, "statistics": [{"type": "Shots on Goal", "value": 13}, {"type": "Shots off Goal", "value": 9}, {"type": "Total Shots", "value": 29}, {"type": "Blocked Shots", "value": 7}, {"type": "Shots insidebox", "value": 10}, {"type": "Shots outsidebox", "value": 19}, {"type": "Fouls", "value": 17}, {"type": "Corner Kicks", "value": 7}, {"type": "Offsides", "value": 1}, {"type": "Ball Possession", "value": "62%"}, {"type": "Yellow Cards", "value": 2}, {"type": "Red Cards", "value": null}, {"type": "Goalkeeper Saves", "value": 2}, {"type": "Total passes", "value": 533}, {"type": "Passes accurate", "value": 459}, {"type": "Passes %", "value": "86%"}, {"type": "expected_goals", "value": null}]}, {"team": {"id": 413, "name": "NEC Nijmegen", "logo": "https://media.api-sports.io/football/teams/413.png"}, "statistics": [{"type": "Shots on Goal", "value": 2}, {"type": "Shots off Goal", "value": 4}, {"type": "Total Shots", "value": 7}, {"type": "Blocked Shots", "value": 1}, {"type": "Shots insidebox", "value": 4}, {"type": "Shots outsidebox", "value": 3}, {"type": "Fouls", "value": 8}, {"type": "Corner Kicks", "value": 3}, {"type": "Offsides", "value": 2}, {"type": "Ball Possession", "value": "38%"}, {"type": "Yellow Cards", "value": 1}, {"type": "Red Cards", "value": null}, {"type": "Goalkeeper Saves", "value": 9}, {"type": "Total passes", "value": 323}, {"type": "Passes accurate", "value": 245}, {"type": "Passes %", "value": "76%"}, {"type": "expected_goals", "value": null}]}]}