{"get": "fixtures/statistics", "parameters": {"fixture": "573166"}, "errors": [], "results": 2, "paging": {"current": 1, "total": 1}, "response": [{"team": {"id": 193, "name": "PEC Zwolle", "logo": "https://media.api-sports.io/football/teams/193.png"}, "statistics": [{"type": "Shots on Goal", "value": 5}, {"type": "Shots off Goal", "value": 9}, {"type": "Total Shots", "value": 19}, {"type": "Blocked Shots", "value": 5}, {"type": "Shots insidebox", "value": 7}, {"type": "Shots outsidebox", "value": 12}, {"type": "Fouls", "value": 15}, {"type": "Corner Kicks", "value": 3}, {"type": "Offsides", "value": 0}, {"type": "Ball Possession", "value": "54%"}, {"type": "Yellow Cards", "value": 3}, {"type": "Red Cards", "value": null}, {"type": "Goalkeeper Saves", "value": 4}, {"type": "Total passes", "value": 501}, {"type": "Passes accurate", "value": 419}, {"type": "Passes %", "value": "84%"}]}, {"team": {"id": 209, "name": "Feyenoord", "logo": "https://media.api-sports.io/football/teams/209.png"}, "statistics": [{"type": "Shots on Goal", "value": 6}, {"type": "Shots off Goal", "value": 6}, {"type": "Total Shots", "value": 13}, {"type": "Blocked Shots", "value": 1}, {"type": "Shots insidebox", "value": 9}, {"type": "Shots outsidebox", "value": 4}, {"type": "Fouls", "value": 11}, {"type": "Corner Kicks", "value": 3}, {"type": "Offsides", "value": 1}, {"type": "Ball Possession", "value": "46%"}, {"type": "Yellow Cards", "value": 1}, {"type": "Red Cards", "value": null}, {"type": "Goalkeeper Saves", "value": 5}, {"type": "Total passes", "value": 424}, {"type": "Passes accurate", "value": 347}, {"type": "Passes %", "value": "82%"}]}]}