{"get": "fixtures/statistics", "parameters": {"fixture": "601131"}, "errors": [], "results": 2, "paging": {"current": 1, "total": 1}, "response": [{"team": {"id": 221, "name": "Belenenses", "logo": "https://media.api-sports.io/football/teams/221.png"}, "statistics": [{"type": "Shots on Goal", "value": 6}, {"type": "Shots off Goal", "value": 5}, {"type": "Total Shots", "value": 14}, {"type": "Blocked Shots", "value": 3}, {"type": "Shots insidebox", "value": 9}, {"type": "Shots outsidebox", "value": 5}, {"type": "Fouls", "value": 20}, {"type": "Corner Kicks", "value": 8}, {"type": "Offsides", "value": 2}, {"type": "Ball Possession", "value": "70%"}, {"type": "Yellow Cards", "value": 2}, {"type": "Red Cards", "value": null}, {"type": "Goalkeeper Saves", "value": 3}, {"type": "Total passes", "value": 510}, {"type": "Passes accurate", "value": 415}, {"type": "Passes %", "value": "81%"}]}, {"team": {"id": 234, "name": "Pacos Ferreira", "logo": "https://media.api-sports.io/football/teams/234.png"}, "statistics": [{"type": "Shots on Goal", "value": 5}, {"type": "Shots off Goal", "value": 4}, {"type": "Total Shots", "value": 9}, {"type": "Blocked Shots", "value": 0}, {"type": "Shots insidebox", "value": 5}, {"type": "Shots outsidebox", "value": 4}, {"type": "Fouls", "value": 11}, {"type": "Corner Kicks", "value": 4}, {"type": "Offsides", "value": 2}, {"type": "Ball Possession", "value": "30%"}, {"type": "Yellow Cards", "value": 2}, {"type": "Red Cards", "value": null}, {"type": "Goalkeeper Saves", "value": 6}, {"type": "Total passes", "value": 213}, {"type": "Passes accurate", "value": 121}, {"type": "Passes %", "value": "57%"}]}]}