{"get": "fixtures/statistics", "parameters": {"fixture": "592232"}, "errors": [], "results": 2, "paging": {"current": 1, "total": 1}, "response": [{"team": {"id": 51, "name": "Brighton", "logo": "https://media.api-sports.io/football/teams/51.png"}, "statistics": [{"type": "Shots on Goal", "value": 3}, {"type": "Shots off Goal", "value": 6}, {"type": "Total Shots", "value": 11}, {"type": "Blocked Shots", "value": 2}, {"type": "Shots insidebox", "value": 7}, {"type": "Shots outsidebox", "value": 4}, {"type": "Fouls", "value": 9}, {"type": "Corner Kicks", "value": 4}, {"type": "Offsides", "value": 2}, {"type": "Ball Possession", "value": "40%"}, {"type": "Yellow Cards", "value": 2}, {"type": "Red Cards", "value": null}, {"type": "Goalkeeper Saves", "value": 1}, {"type": "Total passes", "value": 352}, {"type": "Passes accurate", "value": 272}, {"type": "Passes %", "value": "77%"}]}, {"team": {"id": 40, "name": "Liverpool", "logo": "https://media.api-sports.io/football/teams/40.png"}, "statistics": [{"type": "Shots on Goal", "value": 2}, {"type": "Shots off Goal", "value": 1}, {"type": "Total Shots", "value": 6}, {"type": "Blocked Shots", "value": 3}, {"type": "Shots insidebox", "value": 3}, {"type": "Shots outsidebox", "value": 3}, {"type": "Fouls", "value": 13}, {"type": "Corner Kicks", "value": 3}, {"type": "Offsides", "value": 2}, {"type": "Ball Possession", "value": "60%"}, {"type": "Yellow Cards", "value": 1}, {"type": "Red Cards", "value": null}, {"type": "Goalkeeper Saves", "value": 2}, {"type": "Total passes", "value": 526}, {"type": "Passes accurate", "value": 428}, {"type": "Passes %", "value": "81%"}]}]}