{"get": "fixtures/statistics", "parameters": {"fixture": "847593"}, "errors": [], "results": 2, "paging": {"current": 1, "total": 1}, "response": [{"team": {"id": 1025, "name": "Wolfsberger AC", "logo": "https://media.api-sports.io/football/teams/1025.png"}, "statistics": [{"type": "Shots on Goal", "value": 5}, {"type": "Shots off Goal", "value": 6}, {"type": "Total Shots", "value": 14}, {"type": "Blocked Shots", "value": 3}, {"type": "Shots insidebox", "value": 10}, {"type": "Shots outsidebox", "value": 4}, {"type": "Fouls", "value": 7}, {"type": "Corner Kicks", "value": 4}, {"type": "Offsides", "value": 2}, {"type": "Ball Possession", "value": "66%"}, {"type": "Yellow Cards", "value": 2}, {"type": "Red Cards", "value": null}, {"type": "Goalkeeper Saves", "value": 2}, {"type": "Total passes", "value": 585}, {"type": "Passes accurate", "value": 463}, {"type": "Passes %", "value": "79%"}]}, {"team": {"id": 1405, "name": "Austria Klagenfurt", "logo": "https://media.api-sports.io/football/teams/1405.png"}, "statistics": [{"type": "Shots on Goal", "value": 4}, {"type": "Shots off Goal", "value": 7}, {"type": "Total Shots", "value": 13}, {"type": "Blocked Shots", "value": 2}, {"type": "Shots insidebox", "value": 6}, {"type": "Shots outsidebox", "value": 7}, {"type": "Fouls", "value": 18}, {"type": "Corner Kicks", "value": 5}, {"type": "Offsides", "value": 1}, {"type": "Ball Possession", "value": "34%"}, {"type": "Yellow Cards", "value": 3}, {"type": "Red Cards", "value": null}, {"type": "Goalkeeper Saves", "value": 4}, {"type": "Total passes", "value": 305}, {"type": "Passes accurate", "value": 182}, {"type": "Passes %", "value": "60%"}]}]}