{"get": "fixtures/statistics", "parameters": {"fixture": "865128"}, "errors": [], "results": 2, "paging": {"current": 1, "total": 1}, "response": [{"team": {"id": 345, "name": "Zaglebie Lubin", "logo": "https://media.api-sports.io/football/teams/345.png"}, "statistics": [{"type": "Shots on Goal", "value": 3}, {"type": "Shots off Goal", "value": 5}, {"type": "Total Shots", "value": 15}, {"type": "Blocked Shots", "value": 7}, {"type": "Shots insidebox", "value": 4}, {"type": "Shots outsidebox", "value": 11}, {"type": "Fouls", "value": 13}, {"type": "Corner Kicks", "value": 8}, {"type": "Offsides", "value": 1}, {"type": "Ball Possession", "value": "58%"}, {"type": "Yellow Cards", "value": 0}, {"type": "Red Cards", "value": null}, {"type": "Goalkeeper Saves", "value": 3}, {"type": "Total passes", "value": 459}, {"type": "Passes accurate", "value": 381}, {"type": "Passes %", "value": "83%"}]}, {"team": {"id": 4248, "name": "Radomiak Radom", "logo": "https://media.api-sports.io/football/teams/4248.png"}, "statistics": [{"type": "Shots on Goal", "value": 4}, {"type": "Shots off Goal", "value": 3}, {"type": "Total Shots", "value": 12}, {"type": "Blocked Shots", "value": 5}, {"type": "Shots insidebox", "value": 9}, {"type": "Shots outsidebox", "value": 3}, {"type": "Fouls", "value": 8}, {"type": "Corner Kicks", "value": 6}, {"type": "Offsides", "value": 0}, {"type": "Ball Possession", "value": "42%"}, {"type": "Yellow Cards", "value": 3}, {"type": "Red Cards", "value": null}, {"type": "Goalkeeper Saves", "value": 3}, {"type": "Total passes", "value": 333}, {"type": "Passes accurate", "value": 245}, {"type": "Passes %", "value": "74%"}]}]}