{"get": "fixtures/statistics", "parameters": {"fixture": "157189"}, "errors": [], "results": 2, "paging": {"current": 1, "total": 1}, "response": [{"team": {"id": 50, "name": "Manchester City", "logo": "https://media.api-sports.io/football/teams/50.png"}, "statistics": [{"type": "Shots on Goal", "value": 12}, {"type": "Shots off Goal", "value": 7}, {"type": "Total Shots", "value": 23}, {"type": "Blocked Shots", "value": 4}, {"type": "Shots insidebox", "value": 17}, {"type": "Shots outsidebox", "value": 6}, {"type": "Fouls", "value": 14}, {"type": "Corner Kicks", "value": 6}, {"type": "Offsides", "value": 1}, {"type": "Ball Possession", "value": "62%"}, {"type": "Yellow Cards", "value": 2}, {"type": "Red Cards", "value": null}, {"type": "Goalkeeper Saves", "value": 1}, {"type": "Total passes", "value": 690}, {"type": "Passes accurate", "value": 620}, {"type": "Passes %", "value": "90%"}]}, {"team": {"id": 46, "name": "Leicester", "logo": "https://media.api-sports.io/football/teams/46.png"}, "statistics": [{"type": "Shots on Goal", "value": 2}, {"type": "Shots off Goal", "value": 3}, {"type": "Total Shots", "value": 5}, {"type": "Blocked Shots", "value": 0}, {"type": "Shots insidebox", "value": 3}, {"type": "Shots outsidebox", "value": 2}, {"type": "Fouls", "value": 9}, {"type": "Corner Kicks", "value": 0}, {"type": "Offsides", "value": 3}, {"type": "Ball Possession", "value": "38%"}, {"type": "Yellow Cards", "value": 2}, {"type": "Red Cards", "value": null}, {"type": "Goalkeeper Saves", "value": 9}, {"type": "Total passes", "value": 409}, {"type": "Passes accurate", "value": 332}, {"type": "Passes %", "value": "81%"}]}]}