{"get": "fixtures/statistics", "parameters": {"fixture": "865153"}, "errors": [], "results": 2, "paging": {"current": 1, "total": 1}, "response": [{"team": {"id": 336, "name": "Jagiellonia", "logo": "https://media.api-sports.io/football/teams/336.png"}, "statistics": [{"type": "Shots on Goal", "value": 9}, {"type": "Shots off Goal", "value": 8}, {"type": "Total Shots", "value": 23}, {"type": "Blocked Shots", "value": 6}, {"type": "Shots insidebox", "value": 17}, {"type": "Shots outsidebox", "value": 6}, {"type": "Fouls", "value": 19}, {"type": "Corner Kicks", "value": 2}, {"type": "Offsides", "value": 3}, {"type": "Ball Possession", "value": "46%"}, {"type": "Yellow Cards", "value": 2}, {"type": "Red Cards", "value": null}, {"type": "Goalkeeper Saves", "value": 3}, {"type": "Total passes", "value": 412}, {"type": "Passes accurate", "value": 311}, {"type": "Passes %", "value": "75%"}]}, {"team": {"id": 3493, "name": "Stal Mielec", "logo": "https://media.api-sports.io/football/teams/3493.png"}, "statistics": [{"type": "Shots on Goal", "value": 3}, {"type": "Shots off Goal", "value": 8}, {"type": "Total Shots", "value": 15}, {"type": "Blocked Shots", "value": 4}, {"type": "Shots insidebox", "value": 8}, {"type": "Shots outsidebox", "value": 7}, {"type": "Fouls", "value": 12}, {"type": "Corner Kicks", "value": 3}, {"type": "Offsides", "value": 0}, {"type": "Ball Possession", "value": "54%"}, {"type": "Yellow Cards", "value": 1}, {"type": "Red Cards", "value": null}, {"type": "Goalkeeper Saves", "value": 3}, {"type": "Total passes", "value": 480}, {"type": "Passes accurate", "value": 374}, {"type": "Passes %", "value": "78%"}]}]}