{"get": "fixtures/statistics", "parameters": {"fixture": "865325"}, "errors": [], "results": 2, "paging": {"current": 1, "total": 1}, "response": [{"team": {"id": 349, "name": "Piast Gliwice", "logo": "https://media.api-sports.io/football/teams/349.png"}, "statistics": [{"type": "Shots on Goal", "value": 3}, {"type": "Shots off Goal", "value": 11}, {"type": "Total Shots", "value": 16}, {"type": "Blocked Shots", "value": 2}, {"type": "Shots insidebox", "value": 9}, {"type": "Shots outsidebox", "value": 7}, {"type": "Fouls", "value": 18}, {"type": "Corner Kicks", "value": 6}, {"type": "Offsides", "value": 2}, {"type": "Ball Possession", "value": "37%"}, {"type": "Yellow Cards", "value": 5}, {"type": "Red Cards", "value": null}, {"type": "Goalkeeper Saves", "value": 1}, {"type": "Total passes", "value": 334}, {"type": "Passes accurate", "value": 250}, {"type": "Passes %", "value": "75%"}, {"type": "expected_goals", "value": null}]}, {"team": {"id": 341, "name": "Wisla Plock", "logo": "https://media.api-sports.io/football/teams/341.png"}, "statistics": [{"type": "Shots on Goal", "value": 1}, {"type": "Shots off Goal", "value": 1}, {"type": "Total Shots", "value": 3}, {"type": "Blocked Shots", "value": 1}, {"type": "Shots insidebox", "value": 3}, {"type": "Shots outsidebox", "value": 0}, {"type": "Fouls", "value": 19}, {"type": "Corner Kicks", "value": 2}, {"type": "Offsides", "value": 1}, {"type": "Ball Possession", "value": "63%"}, {"type": "Yellow Cards", "value": 1}, {"type": "Red Cards", "value": null}, {"type": "Goalkeeper Saves", "value": 2}, {"type": "Total passes", "value": 580}, {"type": "Passes accurate", "value": 475}, {"type": "Passes %", "value": "82%"}, {"type": "expected_goals", "value": null}]}]}